curl_pyo3-0.1.1.dist-info/METADATA
curl_pyo3-0.1.1.dist-info/WHEEL
curl_pyo3.libs/libnssutil3-3492aa84.so
curl_pyo3.libs/liblber-2-7eefa761.4.so.2
curl_pyo3.libs/libkrb5support-d0bcff84.so.0
curl_pyo3.libs/libplc4-690d9cce.so
curl_pyo3.libs/libssl-cd1d6220.so.10
curl_pyo3.libs/libldap-2-b8523ca2.4.so.2
curl_pyo3.libs/libkrb5-fcafa220.so.3
curl_pyo3.libs/libnss3-77677daf.so
curl_pyo3.libs/libcom_err-2abe824b.so.2
curl_pyo3.libs/libkeyutils-dfe70bd6.so.1
curl_pyo3.libs/libssl3-b5783e6f.so
curl_pyo3.libs/libsasl2-84219a89.so.3
curl_pyo3.libs/libk5crypto-b1f99d5c.so.3
curl_pyo3.libs/libsmime3-1ce58481.so
curl_pyo3.libs/libcrypto-d3570994.so.10
curl_pyo3.libs/libidn-97d26f25.so.11
curl_pyo3.libs/libssh2-eaeb651a.so.1
curl_pyo3.libs/libselinux-0922c95c.so.1
curl_pyo3.libs/libplds4-c4b42550.so
curl_pyo3.libs/libpcre-9513aab5.so.1
curl_pyo3.libs/libcurl-34c6b10f.so.4
curl_pyo3.libs/libnspr4-4c890ba1.so
curl_pyo3.libs/libcrypt-8f974802.so.1
curl_pyo3.libs/libgssapi_krb5-497db0c6.so.2
curl_pyo3/__init__.py
curl_pyo3/curl_pyo3.cpython-310-x86_64-linux-gnu.so
curl_pyo3-0.1.1.dist-info/RECORD
