Metadata-Version: 2.3
Name: curl_pyo3
Version: 0.1.1
Classifier: Programming Language :: Rust
Classifier: Programming Language :: Python :: Implementation :: CPython
Classifier: Programming Language :: Python :: Implementation :: PyPy
Classifier: Operating System :: OS Independent
Classifier: Topic :: Software Development
Classifier: Intended Audience :: Developers
Summary: libCURL Python Binding
Keywords: curl,rust,ffi
Author-email: Jiacai Liu <dev@liujiacai.net>
License: Apache-2.0
Requires-Python: >=3.8
Project-URL: Repository, https://github.com/jiacai2050/curl-py
Project-URL: Issues, https://github.com/jiacai2050/curl-py/issues
